a_pandas_ex_df2htmlstring/LICENSE
a_pandas_ex_df2htmlstring/README.md
a_pandas_ex_df2htmlstring/__init__.py
a_pandas_ex_df2htmlstring/requirements.txt
a_pandas_ex_df2htmlstring/thirdparty.json
a_pandas_ex_df2htmlstring-0.10.dist-info/LICENSE.rst
a_pandas_ex_df2htmlstring-0.10.dist-info/METADATA
a_pandas_ex_df2htmlstring-0.10.dist-info/WHEEL
a_pandas_ex_df2htmlstring-0.10.dist-info/top_level.txt
a_pandas_ex_df2htmlstring-0.10.dist-info/RECORD
