Metadata-Version: 2.1
Name: a-pandas-ex-df2htmlstring
Version: 0.10
Summary: exports pandas DataFrames/Series as HTML (formatted string that looks like a table!)
Home-page: https://github.com/hansalemaos/a_pandas_ex_df2htmlstring
Author: Johannes Fischer
Author-email: aulasparticularesdealemaosp@gmail.com
License: MIT
Keywords: pandas,html,convert
Classifier: Development Status :: 4 - Beta
Classifier: Programming Language :: Python :: 3 :: Only
Classifier: Programming Language :: Python :: 3.10
Classifier: Topic :: Software Development :: Libraries :: Python Modules
Classifier: Topic :: Utilities
License-File: LICENSE.rst
Requires-Dist: a-pandas-ex-df-to-string
Requires-Dist: pandas
Requires-Dist: touchtouch
